empyrikos/__init__.py
empyrikos/epb_ttest.py
empyrikos/julia_helpers.py
empyrikos-0.1.0.dist-info/licenses/LICENSE
empyrikos-0.1.0.dist-info/METADATA
empyrikos-0.1.0.dist-info/WHEEL
empyrikos-0.1.0.dist-info/top_level.txt
empyrikos-0.1.0.dist-info/RECORD
