Metadata-Version: 2.4
Name: empyrikos
Version: 0.1.0
Summary: Python interface to Empirikos.jl for empirical Bayes methods
Author-email: Nikos Ignatiadis <nikos.ignatiadis@gmail.com>
Project-URL: Homepage, https://github.com/nignatiadis/empyrikos
Project-URL: Bug Reports, https://github.com/nignatiadis/empyrikos/issues
Project-URL: Source, https://github.com/nignatiadis/empyrikos
Classifier: Development Status :: 3 - Alpha
Classifier: Intended Audience :: Science/Research
Classifier: License :: OSI Approved :: MIT License
Classifier: Programming Language :: Python :: 3
Classifier: Programming Language :: Python :: 3.10
Classifier: Programming Language :: Python :: 3.11
Classifier: Programming Language :: Python :: 3.12
Classifier: Topic :: Scientific/Engineering :: Mathematics
Classifier: Topic :: Scientific/Engineering :: Information Analysis
Classifier: Topic :: Scientific/Engineering
Classifier: Operating System :: OS Independent
Requires-Python: >=3.10
License-File: LICENSE
Requires-Dist: juliacall>=0.9.26
Requires-Dist: numpy>=1.20.0
Requires-Dist: scipy>=1.7.0
Requires-Dist: pandas>=1.3.0
Provides-Extra: dev
Requires-Dist: pytest>=6.0; extra == "dev"
Requires-Dist: pytest-cov; extra == "dev"
Requires-Dist: black; extra == "dev"
Requires-Dist: flake8; extra == "dev"
Requires-Dist: mypy; extra == "dev"
Provides-Extra: docs
Requires-Dist: quartodoc>=0.6.0; extra == "docs"
Requires-Dist: jupyter; extra == "docs"
Dynamic: license-file
